{"type":"yearly_choropleth","year":2005,"counts":{"Burkina Faso":55,"Côte d'Ivoire":150,"Ghana":7,"Saudi Arabia":54,"France":10,"Italy":2,"Egypt":3,"United States of America":6,"United Kingdom":3,"Senegal":5,"Liberia":1,"Togo":50,"Central African Rep.":1,"Lebanon":1,"Guinea-Bissau":1,"Mali":7,"Niger":10,"Benin":31,"Algeria":2,"Nigeria":3,"Russia":2,"Morocco":4,"Guinea":2,"Kuwait":7,"India":1,"Iran":11,"Palestine":2,"Zimbabwe":1,"Iraq":3,"South Africa":2,"Qatar":1,"China":1,"Germany":3,"Israel":3,"Sierra Leone":2,"Jordan":2,"Sudan":2,"Libya":1,"Ethiopia":3,"Belgium":2,"Uganda":1,"Congo":1,"Cameroon":1,"Canada":1,"Switzerland":1,"United Arab Emirates":1,"Mauritania":1},"total_articles":464,"total_countries":47,"updatedAt":"2025-09-10T10:00:44.068702"}